poetryexample/__init__.py
poetryexample/main.py
poetryexample-0.2.0.dist-info/WHEEL
poetryexample-0.2.0.dist-info/METADATA
poetryexample-0.2.0.dist-info/RECORD
