Metadata-Version: 2.1
Name: poetryexample
Version: 0.2.0
Summary: 
Author: Alan Bacon
Author-email: alan.bacon@bbc.co.uk
Requires-Python: >=3.4,<4.0
Classifier: Programming Language :: Python :: 3
Classifier: Programming Language :: Python :: 3.4
Classifier: Programming Language :: Python :: 3.5
Classifier: Programming Language :: Python :: 3.6
Classifier: Programming Language :: Python :: 3.7
Requires-Dist: FnF (>=2.0,<3.0)
